digital_clock.v
// digital_clock.v
module digital_clock(
    input clk_1hz, 
    input reset,    
    output reg [6:0] sec_units_display,
    output reg [6:0] sec_tens_display,   
    output reg [6:0] min_units_display,  
    output reg [6:0] min_tens_display,   
    output reg [6:0] hour_units_display,
    output reg [6:0] hour_tens_display
);

    reg [3:0] sec_units = 0;
    reg [2:0] sec_tens = 0;
    reg [3:0] min_units = 0;
    reg [2:0] min_tens = 0;
    reg [3:0] hour_units = 0;
    reg [1:0] hour_tens = 0;

    wire sec_units_carry, sec_tens_carry, min_units_carry, min_tens_carry;
    wire hours_reset;

    assign sec_units_carry = (sec_units == 4'd9);
    assign sec_tens_carry = (sec_tens == 3'd5) && sec_units_carry;
    assign min_units_carry = (min_units == 4'd9) && sec_tens_carry;
    assign min_tens_carry = (min_tens == 3'd5) && min_units_carry;
    assign hours_reset = (hour_tens == 2'd2) && (hour_units == 4'd3) && min_tens_carry;

    always @(posedge clk_1hz or posedge reset) begin
        if (reset) begin
            sec_units <= 0;
            sec_tens <= 0;
            min_units <= 0;
            min_tens <= 0;
            hour_units <= 0;
            hour_tens <= 0;
        end else begin
            if (sec_units == 9)
                sec_units <= 0;
            else
                sec_units <= sec_units + 1;

            if (sec_units_carry) begin
                if (sec_tens == 5)
                    sec_tens <= 0;
                else
                    sec_tens <= sec_tens + 1;
            end

            if (sec_tens_carry) begin
                if (min_units == 9)
                    min_units <= 0;
                else
                    min_units <= min_units + 1;
            end

            if (min_units_carry) begin
                if (min_tens == 5)
                    min_tens <= 0;
                else
                    min_tens <= min_tens + 1;
            end

            if (min_tens_carry) begin
                if (hours_reset) begin
                    hour_units <= 0;
                    hour_tens <= 0;
                end else if ((hour_tens == 2 && hour_units == 3)) begin
                    hour_units <= 0;
                    hour_tens <= 0;
                end else if (hour_units == 9 || (hour_tens == 1 && hour_units == 9)) begin
                    hour_units <= 0;
                    hour_tens <= hour_tens + 1;
                end else begin
                    hour_units <= hour_units + 1;
                end
            end
        end
    end

    function [6:0] bcd_to_7seg(input [3:0] bcd);
        case (bcd)
            4'd0: bcd_to_7seg = 7'b1111110; 
            4'd1: bcd_to_7seg = 7'b0110000; 
            4'd2: bcd_to_7seg = 7'b1101101;
            4'd3: bcd_to_7seg = 7'b1111001;
            4'd4: bcd_to_7seg = 7'b0110011; 
            4'd5: bcd_to_7seg = 7'b1011011; 
            4'd6: bcd_to_7seg = 7'b1011111; 
            4'd7: bcd_to_7seg = 7'b1110000; 
            4'd8: bcd_to_7seg = 7'b1111111; 
            4'd9: bcd_to_7seg = 7'b1111011; 
            default: bcd_to_7seg = 7'b0000000;
        endcase
    endfunction

    always @(posedge clk_1hz or posedge reset) begin
        sec_units_display  = bcd_to_7seg(sec_units);
        sec_tens_display   = bcd_to_7seg({1'b0, sec_tens});
        min_units_display  = bcd_to_7seg(min_units);
        min_tens_display   = bcd_to_7seg({1'b0, min_tens});
        hour_units_display = bcd_to_7seg(hour_units);
        hour_tens_display  = bcd_to_7seg({2'b00, hour_tens});
    end
endmodule

digital_clock_tb.v
`timescale 1s/1ms

module digital_clock_tb;

    reg clk = 0;
    reg reset = 0;

    wire [6:0] sec_units_display;
    wire [6:0] sec_tens_display;
    wire [6:0] min_units_display;
    wire [6:0] min_tens_display;
    wire [6:0] hour_units_display;
    wire [6:0] hour_tens_display;

    digital_clock uut (
        .clk_1hz(clk),
        .reset(reset),
        .sec_units_display(sec_units_display),
        .sec_tens_display(sec_tens_display),
        .min_units_display(min_units_display),
        .min_tens_display(min_tens_display),
        .hour_units_display(hour_units_display),
        .hour_tens_display(hour_tens_display)
    );

    always #0.5 clk = ~clk; // 1Hz clock

    initial begin
        $dumpfile("clock.vcd");
        $dumpvars(0, digital_clock_tb);
        reset = 1;
        #2 reset = 0;

        #100;
        $finish;
    end

endmodule

clock.vcd
$date
	Tue May 13 18:17:57 2025
$end
$version
	Icarus Verilog
$end
$timescale
	1ms
$end
$scope module digital_clock_tb $end
$var wire 7 ! sec_units_display [6:0] $end
$var wire 7 " sec_tens_display [6:0] $end
$var wire 7 # min_units_display [6:0] $end
$var wire 7 $ min_tens_display [6:0] $end
$var wire 7 % hour_units_display [6:0] $end
$var wire 7 & hour_tens_display [6:0] $end
$var reg 1 ' clk $end
$var reg 1 ( reset $end
$scope module uut $end
$var wire 1 ' clk_1hz $end
$var wire 1 ) hours_reset $end
$var wire 1 * min_tens_carry $end
$var wire 1 + min_units_carry $end
$var wire 1 ( reset $end
$var wire 1 , sec_tens_carry $end
$var wire 1 - sec_units_carry $end
$var reg 2 . hour_tens [1:0] $end
$var reg 7 / hour_tens_display [6:0] $end
$var reg 4 0 hour_units [3:0] $end
$var reg 7 1 hour_units_display [6:0] $end
$var reg 3 2 min_tens [2:0] $end
$var reg 7 3 min_tens_display [6:0] $end
$var reg 4 4 min_units [3:0] $end
$var reg 7 5 min_units_display [6:0] $end
$var reg 3 6 sec_tens [2:0] $end
$var reg 7 7 sec_tens_display [6:0] $end
$var reg 4 8 sec_units [3:0] $end
$var reg 7 9 sec_units_display [6:0] $end
$scope function bcd_to_7seg $end
$var reg 4 : bcd [3:0] $end
$upscope $end
$upscope $end
$upscope $end
$enddefinitions $end
$comment Show the parameter values. $end
$dumpall
$end
#0
$dumpvars
b0 :
b1111110 9
b0 8
b1111110 7
b0 6
b1111110 5
b0 4
b1111110 3
b0 2
b1111110 1
b0 0
b1111110 /
b0 .
0-
0,
0+
0*
0)
1(
0'
b1111110 &
b1111110 %
b1111110 $
b1111110 #
b1111110 "
b1111110 !
$end
#500
1'
#1000
0'
#1500
1'
#2000
0'
0(
#2500
b1 8
1'
#3000
0'
#3500
b10 8
b110000 !
b110000 9
b0 :
1'
#4000
0'
#4500
b11 8
b1101101 !
b1101101 9
b0 :
1'
#5000
0'
#5500
b100 8
b1111001 !
b1111001 9
b0 :
1'
#6000
0'
#6500
b101 8
b110011 !
b110011 9
b0 :
1'
#7000
0'
#7500
b110 8
b1011011 !
b1011011 9
b0 :
1'
#8000
0'
#8500
b111 8
b1011111 !
b1011111 9
b0 :
1'
#9000
0'
#9500
b1000 8
b1110000 !
b1110000 9
b0 :
1'
#10000
0'
#10500
1-
b1001 8
b1111111 !
b1111111 9
b0 :
1'
#11000
0'
#11500
b1 6
0-
b0 8
b1111011 !
b1111011 9
b0 :
1'
#12000
0'
#12500
b1 8
b110000 "
b110000 7
b0 :
b1111110 !
b1111110 9
1'
#13000
0'
#13500
b10 8
b110000 !
b110000 9
b0 :
1'
#14000
0'
#14500
b11 8
b1101101 !
b1101101 9
b0 :
1'
#15000
0'
#15500
b100 8
b1111001 !
b1111001 9
b0 :
1'
#16000
0'
#16500
b101 8
b110011 !
b110011 9
b0 :
1'
#17000
0'
#17500
b110 8
b1011011 !
b1011011 9
b0 :
1'
#18000
0'
#18500
b111 8
b1011111 !
b1011111 9
b0 :
1'
#19000
0'
#19500
b1000 8
b1110000 !
b1110000 9
b0 :
1'
#20000
0'
#20500
1-
b1001 8
b1111111 !
b1111111 9
b0 :
1'
#21000
0'
#21500
b10 6
0-
b0 8
b1111011 !
b1111011 9
b0 :
1'
#22000
0'
#22500
b1 8
b1101101 "
b1101101 7
b0 :
b1111110 !
b1111110 9
1'
#23000
0'
#23500
b10 8
b110000 !
b110000 9
b0 :
1'
#24000
0'
#24500
b11 8
b1101101 !
b1101101 9
b0 :
1'
#25000
0'
#25500
b100 8
b1111001 !
b1111001 9
b0 :
1'
#26000
0'
#26500
b101 8
b110011 !
b110011 9
b0 :
1'
#27000
0'
#27500
b110 8
b1011011 !
b1011011 9
b0 :
1'
#28000
0'
#28500
b111 8
b1011111 !
b1011111 9
b0 :
1'
#29000
0'
#29500
b1000 8
b1110000 !
b1110000 9
b0 :
1'
#30000
0'
#30500
1-
b1001 8
b1111111 !
b1111111 9
b0 :
1'
#31000
0'
#31500
b11 6
0-
b0 8
b1111011 !
b1111011 9
b0 :
1'
#32000
0'
#32500
b1 8
b1111001 "
b1111001 7
b0 :
b1111110 !
b1111110 9
1'
#33000
0'
#33500
b10 8
b110000 !
b110000 9
b0 :
1'
#34000
0'
#34500
b11 8
b1101101 !
b1101101 9
b0 :
1'
#35000
0'
#35500
b100 8
b1111001 !
b1111001 9
b0 :
1'
#36000
0'
#36500
b101 8
b110011 !
b110011 9
b0 :
1'
#37000
0'
#37500
b110 8
b1011011 !
b1011011 9
b0 :
1'
#38000
0'
#38500
b111 8
b1011111 !
b1011111 9
b0 :
1'
#39000
0'
#39500
b1000 8
b1110000 !
b1110000 9
b0 :
1'
#40000
0'
#40500
1-
b1001 8
b1111111 !
b1111111 9
b0 :
1'
#41000
0'
#41500
b100 6
0-
b0 8
b1111011 !
b1111011 9
b0 :
1'
#42000
0'
#42500
b1 8
b110011 "
b110011 7
b0 :
b1111110 !
b1111110 9
1'
#43000
0'
#43500
b10 8
b110000 !
b110000 9
b0 :
1'
#44000
0'
#44500
b11 8
b1101101 !
b1101101 9
b0 :
1'
#45000
0'
#45500
b100 8
b1111001 !
b1111001 9
b0 :
1'
#46000
0'
#46500
b101 8
b110011 !
b110011 9
b0 :
1'
#47000
0'
#47500
b110 8
b1011011 !
b1011011 9
b0 :
1'
#48000
0'
#48500
b111 8
b1011111 !
b1011111 9
b0 :
1'
#49000
0'
#49500
b1000 8
b1110000 !
b1110000 9
b0 :
1'
#50000
0'
#50500
1-
b1001 8
b1111111 !
b1111111 9
b0 :
1'
#51000
0'
#51500
b101 6
0-
b0 8
b1111011 !
b1111011 9
b0 :
1'
#52000
0'
#52500
b1 8
b1011011 "
b1011011 7
b0 :
b1111110 !
b1111110 9
1'
#53000
0'
#53500
b10 8
b110000 !
b110000 9
b0 :
1'
#54000
0'
#54500
b11 8
b1101101 !
b1101101 9
b0 :
1'
#55000
0'
#55500
b100 8
b1111001 !
b1111001 9
b0 :
1'
#56000
0'
#56500
b101 8
b110011 !
b110011 9
b0 :
1'
#57000
0'
#57500
b110 8
b1011011 !
b1011011 9
b0 :
1'
#58000
0'
#58500
b111 8
b1011111 !
b1011111 9
b0 :
1'
#59000
0'
#59500
b1000 8
b1110000 !
b1110000 9
b0 :
1'
#60000
0'
#60500
1,
1-
b1001 8
b1111111 !
b1111111 9
b0 :
1'
#61000
0'
#61500
0,
b1 4
b0 6
0-
b0 8
b1111011 !
b1111011 9
b0 :
1'
#62000
0'
#62500
b1 8
b110000 #
b110000 5
b0 :
b1111110 "
b1111110 7
b1111110 !
b1111110 9
1'
#63000
0'
#63500
b10 8
b110000 !
b110000 9
b0 :
1'
#64000
0'
#64500
b11 8
b1101101 !
b1101101 9
b0 :
1'
#65000
0'
#65500
b100 8
b1111001 !
b1111001 9
b0 :
1'
#66000
0'
#66500
b101 8
b110011 !
b110011 9
b0 :
1'
#67000
0'
#67500
b110 8
b1011011 !
b1011011 9
b0 :
1'
#68000
0'
#68500
b111 8
b1011111 !
b1011111 9
b0 :
1'
#69000
0'
#69500
b1000 8
b1110000 !
b1110000 9
b0 :
1'
#70000
0'
#70500
1-
b1001 8
b1111111 !
b1111111 9
b0 :
1'
#71000
0'
#71500
b1 6
0-
b0 8
b1111011 !
b1111011 9
b0 :
1'
#72000
0'
#72500
b1 8
b110000 "
b110000 7
b0 :
b1111110 !
b1111110 9
1'
#73000
0'
#73500
b10 8
b110000 !
b110000 9
b0 :
1'
#74000
0'
#74500
b11 8
b1101101 !
b1101101 9
b0 :
1'
#75000
0'
#75500
b100 8
b1111001 !
b1111001 9
b0 :
1'
#76000
0'
#76500
b101 8
b110011 !
b110011 9
b0 :
1'
#77000
0'
#77500
b110 8
b1011011 !
b1011011 9
b0 :
1'
#78000
0'
#78500
b111 8
b1011111 !
b1011111 9
b0 :
1'
#79000
0'
#79500
b1000 8
b1110000 !
b1110000 9
b0 :
1'
#80000
0'
#80500
1-
b1001 8
b1111111 !
b1111111 9
b0 :
1'
#81000
0'
#81500
b10 6
0-
b0 8
b1111011 !
b1111011 9
b0 :
1'
#82000
0'
#82500
b1 8
b1101101 "
b1101101 7
b0 :
b1111110 !
b1111110 9
1'
#83000
0'
#83500
b10 8
b110000 !
b110000 9
b0 :
1'
#84000
0'
#84500
b11 8
b1101101 !
b1101101 9
b0 :
1'
#85000
0'
#85500
b100 8
b1111001 !
b1111001 9
b0 :
1'
#86000
0'
#86500
b101 8
b110011 !
b110011 9
b0 :
1'
#87000
0'
#87500
b110 8
b1011011 !
b1011011 9
b0 :
1'
#88000
0'
#88500
b111 8
b1011111 !
b1011111 9
b0 :
1'
#89000
0'
#89500
b1000 8
b1110000 !
b1110000 9
b0 :
1'
#90000
0'
#90500
1-
b1001 8
b1111111 !
b1111111 9
b0 :
1'
#91000
0'
#91500
b11 6
0-
b0 8
b1111011 !
b1111011 9
b0 :
1'
#92000
0'
#92500
b1 8
b1111001 "
b1111001 7
b0 :
b1111110 !
b1111110 9
1'
#93000
0'
#93500
b10 8
b110000 !
b110000 9
b0 :
1'
#94000
0'
#94500
b11 8
b1101101 !
b1101101 9
b0 :
1'
#95000
0'
#95500
b100 8
b1111001 !
b1111001 9
b0 :
1'
#96000
0'
#96500
b101 8
b110011 !
b110011 9
b0 :
1'
#97000
0'
#97500
b110 8
b1011011 !
b1011011 9
b0 :
1'
#98000
0'
#98500
b111 8
b1011111 !
b1011111 9
b0 :
1'
#99000
0'
#99500
b1000 8
b1110000 !
b1110000 9
b0 :
1'
#100000
0'
#100500
1-
b1001 8
b1111111 !
b1111111 9
b0 :
1'
#101000
0'
#101500
b100 6
0-
b0 8
b1111011 !
b1111011 9
b0 :
1'
